LICENSE.txt
README.rst
setup.cfg
setup.py
ShabiiNetwork/__init__.py
ShabiiNetwork/module.py
ShabiiNetwork.egg-info/PKG-INFO
ShabiiNetwork.egg-info/SOURCES.txt
ShabiiNetwork.egg-info/dependency_links.txt
ShabiiNetwork.egg-info/top_level.txt