Metadata-Version: 2.1
Name: ShabiiNetwork
Version: 0.0.1
Summary: Graphs and Dijkstra's algorithm by Charawi Detphumi
Home-page: https://github.com/ShabiiPam/ShabiiNetwork
Download-URL: https://github.com/ShabiiPam/ShabiiNetwork/archive/v0.0.1.zip
Author: Charawi Detphumi
Author-email: partgirlcharawi@gmail.com
License: MIT
Keywords: Graph,Dijkstra,Charawi,Detphumi
Classifier: Development Status :: 3 - Alpha
Classifier: Intended Audience :: Education
Classifier: Topic :: Utilities
Classifier: License :: OSI Approved :: MIT License
Classifier: Programming Language :: Python :: 3
Classifier: Programming Language :: Python :: 3.4
Classifier: Programming Language :: Python :: 3.5
Classifier: Programming Language :: Python :: 3.6
Classifier: Programming Language :: Python :: 3.7
Classifier: Programming Language :: Python :: 3.8
Classifier: Programming Language :: Python :: 3.9
Classifier: Programming Language :: Python :: 3.10
License-File: LICENSE.txt
